sharepointio/sharepointio.py
sharepointio-0.0.4.dist-info/METADATA
sharepointio-0.0.4.dist-info/WHEEL
sharepointio-0.0.4.dist-info/top_level.txt
sharepointio-0.0.4.dist-info/RECORD
