Metadata-Version: 2.1
Name: sharepointio
Version: 0.0.4
Summary: An easy use of Office365-REST-Python-Client to download/upload/list sharepoint files
Home-page: UNKNOWN
Author: Thomas PICAL, Hervé MIGNOT
Author-email: no-reply@noreply.com
License: Apache 2.0
Platform: UNKNOWN
Classifier: Development Status :: 2 - Pre-Alpha
Classifier: Topic :: Internet :: WWW/HTTP
Classifier: Topic :: Communications :: File Sharing
Classifier: Topic :: Office/Business
Classifier: Topic :: Utilities
Classifier: Intended Audience :: Developers
Classifier: Programming Language :: Python :: 3.8
Classifier: License :: OSI Approved :: Apache Software License
Classifier: Operating System :: OS Independent
Requires-Dist: Office365-REST-Python-Client
Requires-Dist: temp
Requires-Dist: pathlib2
